pyident/__init__.py
pyident/exceptions.py
pyident/zibal.py
pyident-0.1.1.dist-info/LICENSE
pyident-0.1.1.dist-info/METADATA
pyident-0.1.1.dist-info/WHEEL
pyident-0.1.1.dist-info/RECORD
