Metadata-Version: 2.1
Name: pyident
Version: 0.1.1
Summary: A Library to help you identify you users using Zibal API
License: MIT
Author: Fateme Fouladkar
Author-email: fatemefuoladkar@gmail.com
Requires-Python: >=3.12,<4.0
Classifier: License :: OSI Approved :: MIT License
Classifier: Programming Language :: Python :: 3
Classifier: Programming Language :: Python :: 3.12
Requires-Dist: requests (>=2.32.3,<3.0.0)
